GBU/__init__.py
Ginger_Bluetooth_Utils-0.0.1.dist-info/LICENSE
Ginger_Bluetooth_Utils-0.0.1.dist-info/METADATA
Ginger_Bluetooth_Utils-0.0.1.dist-info/WHEEL
Ginger_Bluetooth_Utils-0.0.1.dist-info/top_level.txt
Ginger_Bluetooth_Utils-0.0.1.dist-info/RECORD
