Metadata-Version: 2.1
Name: Ginger-Bluetooth-Utils
Version: 0.0.1
Summary: A relatively useless Tkinter program that connects to Bluetooth devices.
Home-page: https://github.com/GingerIndustries/Ginger-Bluetooth-Utils
Author: Ginger Industries
Author-email: 
License: UNKNOWN
Platform: UNKNOWN
Classifier: Programming Language :: Python :: 3
Classifier: License :: OSI Approved :: MIT License
Classifier: Operating System :: OS Independent
Requires-Python: >=3.6
